mimic_cxr_jpg_loader/__init__.py
mimic_cxr_jpg_loader/dataset.py
mimic_cxr_jpg_loader/modifiers.py
mimic_cxr_jpg_loader-0.0.8.dist-info/METADATA
mimic_cxr_jpg_loader-0.0.8.dist-info/WHEEL
mimic_cxr_jpg_loader-0.0.8.dist-info/licenses/LICENSE
mimic_cxr_jpg_loader-0.0.8.dist-info/RECORD
