Metadata-Version: 2.4
Name: mimic_cxr_jpg_loader
Version: 0.0.8
Summary: A package which facilitates loading data from the MIMIC-CXR-JPG dataset
Project-URL: Homepage, https://github.com/filipepcampos/mimic-cxr-jpg-loader
Project-URL: Issues, https://github.com/filipepcampos/mimic-cxr-jpg-loader/issues
Author-email: Filipe Campos <filipepcampos24@gmail.com>
License-File: LICENSE
Classifier: License :: OSI Approved :: MIT License
Classifier: Operating System :: OS Independent
Classifier: Programming Language :: Python :: 3
Requires-Python: >=3.8
Requires-Dist: pandas
Requires-Dist: pillow
